cds_dojson/__init__.py
cds_dojson/cli.py
cds_dojson/matcher.py
cds_dojson/overdo.py
cds_dojson/utils.py
cds_dojson/marc21/__init__.py
cds_dojson/marc21/utils.py
cds_dojson/marc21/fields/__init__.py
cds_dojson/marc21/fields/base.py
cds_dojson/marc21/fields/utils.py
cds_dojson/marc21/fields/books/__init__.py
cds_dojson/marc21/fields/books/base.py
cds_dojson/marc21/fields/books/book.py
cds_dojson/marc21/fields/books/errors.py
cds_dojson/marc21/fields/books/journal.py
cds_dojson/marc21/fields/books/multipart.py
cds_dojson/marc21/fields/books/serial.py
cds_dojson/marc21/fields/books/standard.py
cds_dojson/marc21/fields/books/utils.py
cds_dojson/marc21/fields/books/values_mapping.py
cds_dojson/marc21/fields/rdm/__init__.py
cds_dojson/marc21/fields/rdm/base.py
cds_dojson/marc21/fields/videos/__init__.py
cds_dojson/marc21/fields/videos/base.py
cds_dojson/marc21/fields/videos/project.py
cds_dojson/marc21/fields/videos/utils.py
cds_dojson/marc21/fields/videos/video.py
cds_dojson/marc21/models/__init__.py
cds_dojson/marc21/models/base.py
cds_dojson/marc21/models/books/__init__.py
cds_dojson/marc21/models/books/base.py
cds_dojson/marc21/models/books/book.py
cds_dojson/marc21/models/books/journal.py
cds_dojson/marc21/models/books/multipart.py
cds_dojson/marc21/models/books/serial.py
cds_dojson/marc21/models/books/standard.py
cds_dojson/marc21/models/videos/__init__.py
cds_dojson/marc21/models/videos/base.py
cds_dojson/marc21/models/videos/project.py
cds_dojson/marc21/models/videos/video.py
cds_dojson/schemas/__init__.py
cds_dojson/schemas/transform.py
cds_dojson/schemas/categories/category-v1.0.0.json
cds_dojson/schemas/deposits/deposit-cds-v1.0.0.json
cds_dojson/schemas/deposits/records/base-v1.0.0.json
cds_dojson/schemas/deposits/records/videos/project/project-v1.0.0.json
cds_dojson/schemas/deposits/records/videos/project/project_src-v1.0.0.json
cds_dojson/schemas/deposits/records/videos/video/video-v1.0.0.json
cds_dojson-0.13.0.dist-info/AUTHORS.rst
cds_dojson-0.13.0.dist-info/LICENSE
cds_dojson-0.13.0.dist-info/METADATA
cds_dojson-0.13.0.dist-info/WHEEL
cds_dojson-0.13.0.dist-info/entry_points.txt
cds_dojson-0.13.0.dist-info/top_level.txt
cds_dojson-0.13.0.dist-info/RECORD
