Metadata-Version: 2.1
Name: cds-dojson
Version: 0.13.0
Summary: UNKNOWN
Home-page: UNKNOWN
License: UNKNOWN
Platform: UNKNOWN
Requires-Python: >=3.9
License-File: LICENSE
License-File: AUTHORS.rst
Requires-Dist: arrow>=0.7.0
Requires-Dist: dojson>=1.3.2
Requires-Dist: invenio-query-parser>=0.5.0
Requires-Dist: requests>=2.17.3
Requires-Dist: pycountry>=17.5.14
Requires-Dist: PyYAML>=3.13
Requires-Dist: python-dateutil>=2.7.3
Provides-Extra: docs
Requires-Dist: Sphinx>=1.3; extra == "docs"
Provides-Extra: tests
Requires-Dist: check-manifest>=0.25; extra == "tests"
Requires-Dist: coverage<6,>=5.3; extra == "tests"
Requires-Dist: invenio-jsonschemas<1.1.2,>=1.0.0a5; extra == "tests"
Requires-Dist: jsonpatch>=1.11; extra == "tests"
Requires-Dist: jsonref>=0.1; extra == "tests"
Requires-Dist: jsonresolver>=0.1.0; extra == "tests"
Requires-Dist: jsonschema>=2.5.1; extra == "tests"
Requires-Dist: mock>=1.3.0; extra == "tests"
Requires-Dist: pytest-runner>=2.6.2; extra == "tests"
Requires-Dist: pydocstyle>=1.0.0; extra == "tests"
Requires-Dist: pycodestyle>=1.0.0; extra == "tests"
Requires-Dist: pytest-cache>=1.0; extra == "tests"
Requires-Dist: pytest-cov>=2.10.1; extra == "tests"
Requires-Dist: pytest-isort>=1.2.0; extra == "tests"
Requires-Dist: pytest-pep8>=1.0.6; extra == "tests"
Requires-Dist: pytest>=4.0.0; extra == "tests"
Requires-Dist: pycountry>=17.5.14; extra == "tests"
Requires-Dist: Sphinx>=1.3; extra == "tests"
